README.md
setup.cfg
setup.py
eis/__init__.py
eis/tenant/__init__.py
eis/tenant/api_client.py
eis/tenant/configuration.py
eis/tenant/exceptions.py
eis/tenant/model_utils.py
eis/tenant/rest.py
eis/tenant/api/__init__.py
eis/tenant/api/custom_schema_api.py
eis/tenant/api/dashboard_api.py
eis/tenant/api/dashboard_group_api.py
eis/tenant/api/data_report_api.py
eis/tenant/api/data_report_executor_api.py
eis/tenant/api/delete_organization_invitations_api.py
eis/tenant/api/health_check_api.py
eis/tenant/api/invite_organizations_api.py
eis/tenant/api/invite_users_api.py
eis/tenant/api/list_organization_invitations_api.py
eis/tenant/api/organization_migration_api.py
eis/tenant/api/organizations_api.py
eis/tenant/api/re_invite_an_organization_api.py
eis/tenant/api/roles_api.py
eis/tenant/api/settings_api.py
eis/tenant/api/users_api.py
eis/tenant/apis/__init__.py
eis/tenant/model/__init__.py
eis/tenant/model/assign_user_roles_request_dto.py
eis/tenant/model/assign_user_roles_response_class.py
eis/tenant/model/batch_delete_request_dto.py
eis/tenant/model/batch_delete_response_class.py
eis/tenant/model/create_custom_schema_request_dto.py
eis/tenant/model/create_custom_schema_response_class.py
eis/tenant/model/create_dashboard_group_request_dto.py
eis/tenant/model/create_dashboard_group_response_class.py
eis/tenant/model/create_dashboard_request_dto.py
eis/tenant/model/create_dashboard_response_class.py
eis/tenant/model/create_dashboard_v2_request_dto.py
eis/tenant/model/create_dashboard_v2_response_class.py
eis/tenant/model/create_data_report_request_dto.py
eis/tenant/model/create_data_report_response_class.py
eis/tenant/model/create_organization_migration_request_dto.py
eis/tenant/model/create_organization_migration_response_class.py
eis/tenant/model/create_resources_migration_request_dto.py
eis/tenant/model/create_tenant_request_dto.py
eis/tenant/model/custom_field_dto.py
eis/tenant/model/custom_schema_class.py
eis/tenant/model/dashboard_class.py
eis_tenants.egg-info/PKG-INFO
eis_tenants.egg-info/SOURCES.txt
eis_tenants.egg-info/dependency_links.txt
eis_tenants.egg-info/requires.txt
eis_tenants.egg-info/top_level.txt
