Metadata-Version: 2.1
Name: eis-tenants
Version: 1.30.0
Summary: EMIL Tenant Service
Home-page: UNKNOWN
Author: Contact us
Author-email: kontakt@emil.de
License: UNKNOWN
Keywords: OpenAPI,OpenAPI-Generator,EMIL Tenant Service
Platform: UNKNOWN
Requires-Python: >=3.6
